MANIFEST.in
README.md
setup.py
openspeechlib/__init__.py
openspeechlib.egg-info/PKG-INFO
openspeechlib.egg-info/SOURCES.txt
openspeechlib.egg-info/dependency_links.txt
openspeechlib.egg-info/not-zip-safe
openspeechlib.egg-info/requires.txt
openspeechlib.egg-info/top_level.txt
openspeechlib/corpora/__init__.py
openspeechlib/corpora/base.py
openspeechlib/corpora/librivox.py
openspeechlib/corpora/tests/__init__.py
openspeechlib/corpora/tests/tests_base.py
openspeechlib/corpora/tests/tests_librivox.py
openspeechlib/feature_extraction/__init__.py
openspeechlib/feature_extraction/mfcc.py
openspeechlib/feature_extraction/tests/__init__.py
openspeechlib/feature_extraction/tests/tests_mfcc.py
openspeechlib/feature_extraction/utils/__init__.py
openspeechlib/feature_extraction/utils/delta.py
openspeechlib/feature_extraction/utils/mel_scale.py
openspeechlib/feature_extraction/utils/tests/__init__.py
openspeechlib/feature_extraction/utils/tests/delta.py
openspeechlib/segmentation/__init__.py
openspeechlib/segmentation/silence_segmentation.py
openspeechlib/segmentation/tests/__init__.py
openspeechlib/segmentation/tests/tests_silence_segmentation.py
openspeechlib/utils/__init__.py
openspeechlib/utils/file.py
openspeechlib/utils/filters.py
openspeechlib/utils/http.py
openspeechlib/utils/signal.py
openspeechlib/utils/windows.py
openspeechlib/utils/tests/__init__.py
openspeechlib/utils/tests/tests_windows.py