Metadata-Version: 2.1
Name: openspeechlib
Version: 0.0.2
Summary: Useful libraries to process and generate speech
Home-page: https://github.com/open-speech-org/openspeech
Author: contraslash S.A.S.
Author-email: ma0@contraslash.com
License: MIT
Project-URL: Bug Reports, https://github.com/open-speech-org/openspeech/issues
Project-URL: Source, https://github.com/open-speech-org/openspeech
Project-URL: Contraslash, https://contraslash.com/
Platform: UNKNOWN
Classifier: Development Status :: 3 - Alpha
Classifier: Intended Audience :: Developers
Classifier: License :: OSI Approved :: MIT License
Classifier: Programming Language :: Python :: 3
